point_spectra_gui/__init__.py
point_spectra_gui/__main__.py
point_spectra_gui/core/About.py
point_spectra_gui/core/AboutQt.py
point_spectra_gui/core/BaselineRemoval.py
point_spectra_gui/core/Clustering.py
point_spectra_gui/core/CombineDataSets.py
point_spectra_gui/core/CrossValidation.py
point_spectra_gui/core/DataTable.py
point_spectra_gui/core/DimensionalityReduction.py
point_spectra_gui/core/Interpolation.py
point_spectra_gui/core/LoadData.py
point_spectra_gui/core/MainWindow.py
point_spectra_gui/core/MaskData.py
point_spectra_gui/core/MultiplyByVector.py
point_spectra_gui/core/Normalization.py
point_spectra_gui/core/OutlierRemoval.py
point_spectra_gui/core/OutputFolder.py
point_spectra_gui/core/PeakAreas.py
point_spectra_gui/core/Plot.py
point_spectra_gui/core/PlotSpectra.py
point_spectra_gui/core/Plot_ICA_PCA.py
point_spectra_gui/core/ReadChemCamData.py
point_spectra_gui/core/RegressionPredict.py
point_spectra_gui/core/RegressionTrain.py
point_spectra_gui/core/RemoveRows.py
point_spectra_gui/core/RenameData.py
point_spectra_gui/core/RestoreTrainedModel.py
point_spectra_gui/core/SaveTrainedModel.py
point_spectra_gui/core/SpecDeriv.py
point_spectra_gui/core/SplitDataset.py
point_spectra_gui/core/StratifiedFolds.py
point_spectra_gui/core/SubmodelBlend.py
point_spectra_gui/core/WriteToCSV.py
point_spectra_gui/core/__init__.py
point_spectra_gui/core/setShortcuts.py
point_spectra_gui/core/baselineRemovalMethods/ALS.py
point_spectra_gui/core/baselineRemovalMethods/AirPLS.py
point_spectra_gui/core/baselineRemovalMethods/Dietrich.py
point_spectra_gui/core/baselineRemovalMethods/FABC.py
point_spectra_gui/core/baselineRemovalMethods/KK.py
point_spectra_gui/core/baselineRemovalMethods/Mario.py
point_spectra_gui/core/baselineRemovalMethods/Median.py
point_spectra_gui/core/baselineRemovalMethods/Polyfit.py
point_spectra_gui/core/baselineRemovalMethods/Rubberband.py
point_spectra_gui/core/baselineRemovalMethods/SWT.py
point_spectra_gui-3.5.10.dist-info/METADATA
point_spectra_gui-3.5.10.dist-info/RECORD
point_spectra_gui-3.5.10.dist-info/WHEEL
point_spectra_gui-3.5.10.dist-info/entry_points.txt
point_spectra_gui-3.5.10.dist-info/top_level.txt
