Metadata-Version: 2.1
Name: point-spectra-gui
Version: 3.5.10
Summary: A PDART-funded effort to design a spectral analysis tool for LIBS (and other) spectra
Home-page: https://github.com/USGS-Astrogeology/PySAT
Author: Ryan B. Anderson, Nicholas Finch
Author-email: rbanderson@usgs.gov, ngf4@nau.edu
License: Public Domain
Keywords: PYSAT LIBS PDART Point Spectra
Platform: UNKNOWN
Classifier: Programming Language :: Python :: 3.5
Classifier: Programming Language :: Python :: 3.6
Classifier: Operating System :: Microsoft :: Windows
Classifier: Operating System :: MacOS
Classifier: Operating System :: POSIX :: Linux
Classifier: Topic :: Scientific/Engineering
Requires-Dist: sklearn
Requires-Dist: qtmodern
Requires-Dist: libpysat
